{
  "timestamp": "2026-01-29T17:28:38Z",
  "timestamp_local": "2026-01-30 01:28:38",
  "data_points": 79,
  "reddit": {
    "total_subscribers": 3693,
    "delta_subscribers": 708,
    "total_active": 0,
    "total_posts_24h": 73,
    "total_comments": 428,
    "total_upvotes": 189,
    "subreddits": [
      {
        "name": "r/clawdbot",
        "key": "clawdbot",
        "subscribers": 2714,
        "active": 0,
        "posts_24h": 39,
        "comments": 341,
        "avg_score": 2,
        "total_upvotes": 73,
        "top_score": 15
      },
      {
        "name": "r/moltbot",
        "key": "moltbot",
        "subscribers": 619,
        "active": 0,
        "posts_24h": 24,
        "comments": 61,
        "avg_score": 1,
        "total_upvotes": 40,
        "top_score": 4
      },
      {
        "name": "r/moltbothub",
        "key": "moltbothub",
        "subscribers": 65,
        "active": 0,
        "posts_24h": 4,
        "comments": 5,
        "avg_score": 1,
        "total_upvotes": 13,
        "top_score": 3
      },
      {
        "name": "r/moltbothq",
        "key": "moltbothq",
        "subscribers": 37,
        "active": 0,
        "posts_24h": 0,
        "comments": 1,
        "avg_score": 2,
        "total_upvotes": 4,
        "top_score": 3
      },
      {
        "name": "r/moltbotcommunity",
        "key": "moltbotcommunity",
        "subscribers": 258,
        "active": 0,
        "posts_24h": 6,
        "comments": 20,
        "avg_score": 3,
        "total_upvotes": 59,
        "top_score": 10
      }
    ]
  },
  "github": {
    "stars": 101170,
    "stars_delta": 10096,
    "forks": 14107,
    "forks_delta": 1662,
    "open_issues": 1113
  }
}