{
  "timestamp": "2026-02-09T10:40:13Z",
  "timestamp_local": "2026-02-09 18:40:13",
  "data_points": 888,
  "reddit": {
    "total_subscribers": 22997,
    "delta_subscribers": 1,
    "total_active": 0,
    "total_posts_24h": 54,
    "total_comments": 234,
    "total_upvotes": 369,
    "subreddits": [
      {
        "name": "r/clawdbot",
        "key": "clawdbot",
        "subscribers": 16697,
        "active": 0,
        "posts_24h": 48,
        "comments": 220,
        "avg_score": 7,
        "total_upvotes": 347,
        "top_score": 202
      },
      {
        "name": "r/moltbot",
        "key": "moltbot",
        "subscribers": 5443,
        "active": 0,
        "posts_24h": 6,
        "comments": 14,
        "avg_score": 4,
        "total_upvotes": 22,
        "top_score": 15
      },
      {
        "name": "r/moltbothub",
        "key": "moltbothub",
        "subscribers": 109,
        "active": 0,
        "posts_24h": 0,
        "comments": 0,
        "avg_score": 0,
        "total_upvotes": 0,
        "top_score": 0
      },
      {
        "name": "r/moltbothq",
        "key": "moltbothq",
        "subscribers": 79,
        "active": 0,
        "posts_24h": 0,
        "comments": 0,
        "avg_score": 0,
        "total_upvotes": 0,
        "top_score": 0
      },
      {
        "name": "r/moltbotcommunity",
        "key": "moltbotcommunity",
        "subscribers": 669,
        "active": 0,
        "posts_24h": 0,
        "comments": 0,
        "avg_score": 0,
        "total_upvotes": 0,
        "top_score": 0
      }
    ]
  },
  "github": {
    "stars": 65488,
    "stars_delta": 2,
    "forks": 5020,
    "forks_delta": 0,
    "open_issues": 6375
  }
}