{
  "timestamp": "2026-02-09T04:40:12Z",
  "timestamp_local": "2026-02-09 12:40:12",
  "data_points": 852,
  "reddit": {
    "total_subscribers": 22729,
    "delta_subscribers": 5,
    "total_active": 0,
    "total_posts_24h": 58,
    "total_comments": 306,
    "total_upvotes": 310,
    "subreddits": [
      {
        "name": "r/clawdbot",
        "key": "clawdbot",
        "subscribers": 16495,
        "active": 0,
        "posts_24h": 48,
        "comments": 285,
        "avg_score": 6,
        "total_upvotes": 286,
        "top_score": 152
      },
      {
        "name": "r/moltbot",
        "key": "moltbot",
        "subscribers": 5380,
        "active": 0,
        "posts_24h": 10,
        "comments": 21,
        "avg_score": 2,
        "total_upvotes": 24,
        "top_score": 13
      },
      {
        "name": "r/moltbothub",
        "key": "moltbothub",
        "subscribers": 109,
        "active": 0,
        "posts_24h": 0,
        "comments": 0,
        "avg_score": 0,
        "total_upvotes": 0,
        "top_score": 0
      },
      {
        "name": "r/moltbothq",
        "key": "moltbothq",
        "subscribers": 79,
        "active": 0,
        "posts_24h": 0,
        "comments": 0,
        "avg_score": 0,
        "total_upvotes": 0,
        "top_score": 0
      },
      {
        "name": "r/moltbotcommunity",
        "key": "moltbotcommunity",
        "subscribers": 666,
        "active": 0,
        "posts_24h": 0,
        "comments": 0,
        "avg_score": 0,
        "total_upvotes": 0,
        "top_score": 0
      }
    ]
  },
  "github": {
    "stars": 65413,
    "stars_delta": 3,
    "forks": 5009,
    "forks_delta": 0,
    "open_issues": 6478
  }
}