{
  "timestamp": "2026-02-09T14:50:12Z",
  "timestamp_local": "2026-02-09 22:50:12",
  "data_points": 913,
  "reddit": {
    "total_subscribers": 23159,
    "delta_subscribers": 4,
    "total_active": 0,
    "total_posts_24h": 67,
    "total_comments": 220,
    "total_upvotes": 417,
    "subreddits": [
      {
        "name": "r/clawdbot",
        "key": "clawdbot",
        "subscribers": 16813,
        "active": 0,
        "posts_24h": 54,
        "comments": 202,
        "avg_score": 7,
        "total_upvotes": 398,
        "top_score": 220
      },
      {
        "name": "r/moltbot",
        "key": "moltbot",
        "subscribers": 5486,
        "active": 0,
        "posts_24h": 12,
        "comments": 18,
        "avg_score": 2,
        "total_upvotes": 18,
        "top_score": 5
      },
      {
        "name": "r/moltbothub",
        "key": "moltbothub",
        "subscribers": 109,
        "active": 0,
        "posts_24h": 0,
        "comments": 0,
        "avg_score": 0,
        "total_upvotes": 0,
        "top_score": 0
      },
      {
        "name": "r/moltbothq",
        "key": "moltbothq",
        "subscribers": 79,
        "active": 0,
        "posts_24h": 0,
        "comments": 0,
        "avg_score": 0,
        "total_upvotes": 0,
        "top_score": 0
      },
      {
        "name": "r/moltbotcommunity",
        "key": "moltbotcommunity",
        "subscribers": 672,
        "active": 0,
        "posts_24h": 1,
        "comments": 0,
        "avg_score": 1,
        "total_upvotes": 1,
        "top_score": 1
      }
    ]
  },
  "github": {
    "stars": 65528,
    "stars_delta": 0,
    "forks": 5025,
    "forks_delta": 0,
    "open_issues": 6429
  }
}