{
  "timestamp": "2026-02-09T17:00:13Z",
  "timestamp_local": "2026-02-10 01:00:13",
  "data_points": 926,
  "reddit": {
    "total_subscribers": 23255,
    "delta_subscribers": 6,
    "total_active": 0,
    "total_posts_24h": 72,
    "total_comments": 225,
    "total_upvotes": 263,
    "subreddits": [
      {
        "name": "r/clawdbot",
        "key": "clawdbot",
        "subscribers": 16891,
        "active": 0,
        "posts_24h": 58,
        "comments": 201,
        "avg_score": 4,
        "total_upvotes": 246,
        "top_score": 54
      },
      {
        "name": "r/moltbot",
        "key": "moltbot",
        "subscribers": 5504,
        "active": 0,
        "posts_24h": 13,
        "comments": 24,
        "avg_score": 1,
        "total_upvotes": 16,
        "top_score": 3
      },
      {
        "name": "r/moltbothub",
        "key": "moltbothub",
        "subscribers": 109,
        "active": 0,
        "posts_24h": 0,
        "comments": 0,
        "avg_score": 0,
        "total_upvotes": 0,
        "top_score": 0
      },
      {
        "name": "r/moltbothq",
        "key": "moltbothq",
        "subscribers": 79,
        "active": 0,
        "posts_24h": 0,
        "comments": 0,
        "avg_score": 0,
        "total_upvotes": 0,
        "top_score": 0
      },
      {
        "name": "r/moltbotcommunity",
        "key": "moltbotcommunity",
        "subscribers": 672,
        "active": 0,
        "posts_24h": 1,
        "comments": 0,
        "avg_score": 1,
        "total_upvotes": 1,
        "top_score": 1
      }
    ]
  },
  "github": {
    "stars": 65544,
    "stars_delta": 2,
    "forks": 5024,
    "forks_delta": 0,
    "open_issues": 6444
  }
}