{
  "timestamp": "2026-02-11T01:10:13Z",
  "timestamp_local": "2026-02-11 09:10:13",
  "data_points": 1001,
  "reddit": {
    "total_subscribers": 24812,
    "delta_subscribers": 4,
    "total_active": 0,
    "total_posts_24h": 78,
    "total_comments": 340,
    "total_upvotes": 457,
    "subreddits": [
      {
        "name": "r/clawdbot",
        "key": "clawdbot",
        "subscribers": 18128,
        "active": 0,
        "posts_24h": 63,
        "comments": 327,
        "avg_score": 7,
        "total_upvotes": 429,
        "top_score": 147
      },
      {
        "name": "r/moltbot",
        "key": "moltbot",
        "subscribers": 5814,
        "active": 0,
        "posts_24h": 13,
        "comments": 13,
        "avg_score": 2,
        "total_upvotes": 25,
        "top_score": 6
      },
      {
        "name": "r/moltbothub",
        "key": "moltbothub",
        "subscribers": 109,
        "active": 0,
        "posts_24h": 0,
        "comments": 0,
        "avg_score": 0,
        "total_upvotes": 0,
        "top_score": 0
      },
      {
        "name": "r/moltbothq",
        "key": "moltbothq",
        "subscribers": 79,
        "active": 0,
        "posts_24h": 1,
        "comments": 0,
        "avg_score": 1,
        "total_upvotes": 1,
        "top_score": 1
      },
      {
        "name": "r/moltbotcommunity",
        "key": "moltbotcommunity",
        "subscribers": 682,
        "active": 0,
        "posts_24h": 1,
        "comments": 0,
        "avg_score": 2,
        "total_upvotes": 2,
        "top_score": 2
      }
    ]
  },
  "github": {
    "stars": 65904,
    "stars_delta": 2,
    "forks": 5066,
    "forks_delta": 0,
    "open_issues": 6638
  }
}