{
  "timestamp": "2026-02-06T10:10:13Z",
  "timestamp_local": "2026-02-06 18:10:13",
  "data_points": 453,
  "reddit": {
    "total_subscribers": 19252,
    "delta_subscribers": 7,
    "total_active": 0,
    "total_posts_24h": 100,
    "total_comments": 439,
    "total_upvotes": 565,
    "subreddits": [
      {
        "name": "r/clawdbot",
        "key": "clawdbot",
        "subscribers": 13959,
        "active": 0,
        "posts_24h": 90,
        "comments": 416,
        "avg_score": 6,
        "total_upvotes": 519,
        "top_score": 227
      },
      {
        "name": "r/moltbot",
        "key": "moltbot",
        "subscribers": 4487,
        "active": 0,
        "posts_24h": 9,
        "comments": 23,
        "avg_score": 5,
        "total_upvotes": 45,
        "top_score": 19
      },
      {
        "name": "r/moltbothub",
        "key": "moltbothub",
        "subscribers": 105,
        "active": 0,
        "posts_24h": 0,
        "comments": 0,
        "avg_score": 0,
        "total_upvotes": 0,
        "top_score": 0
      },
      {
        "name": "r/moltbothq",
        "key": "moltbothq",
        "subscribers": 78,
        "active": 0,
        "posts_24h": 0,
        "comments": 0,
        "avg_score": 0,
        "total_upvotes": 0,
        "top_score": 0
      },
      {
        "name": "r/moltbotcommunity",
        "key": "moltbotcommunity",
        "subscribers": 623,
        "active": 0,
        "posts_24h": 1,
        "comments": 0,
        "avg_score": 1,
        "total_upvotes": 1,
        "top_score": 1
      }
    ]
  },
  "github": {
    "stars": 64691,
    "stars_delta": 5,
    "forks": 4918,
    "forks_delta": 0,
    "open_issues": 6307
  }
}